nicecache/__init__.py
nicecache/nicecache.py
nicecache-0.0.1.dist-info/METADATA
nicecache-0.0.1.dist-info/WHEEL
nicecache-0.0.1.dist-info/top_level.txt
nicecache-0.0.1.dist-info/RECORD
