Metadata-Version: 2.1
Name: nicecache
Version: 0.0.1
Summary: Cache data between program runs (then forget about it!)
Home-page: https://github.com/jxmorris12/nicecache
Author: Jack Morris
Author-email: jxmorris12@gmail.com
License: GNU GPL
Platform: UNKNOWN
Requires-Dist: diskcache
